dasy_hy-0.24.2.data/data/get_version/get_version.py
hy/__init__.py
hy/__main__.py
hy/_compat.py
hy/cmdline.py
hy/compiler.py
hy/completer.py
hy/errors.py
hy/importer.py
hy/macros.py
hy/model_patterns.py
hy/models.py
hy/pyops.hy
hy/reserved.hy
hy/scoping.py
hy/__pycache__/pyops.cpython-310.pyc
hy/__pycache__/reserved.cpython-310.pyc
hy/core/__init__.py
hy/core/hy_repr.hy
hy/core/macros.hy
hy/core/result_macros.py
hy/core/util.hy
hy/core/__pycache__/hy_repr.cpython-310.pyc
hy/core/__pycache__/macros.cpython-310.pyc
hy/core/__pycache__/util.cpython-310.pyc
hy/reader/__init__.py
hy/reader/exceptions.py
hy/reader/hy_reader.py
hy/reader/mangling.py
hy/reader/reader.py
dasy_hy-0.24.2.dist-info/AUTHORS
dasy_hy-0.24.2.dist-info/LICENSE
dasy_hy-0.24.2.dist-info/METADATA
dasy_hy-0.24.2.dist-info/WHEEL
dasy_hy-0.24.2.dist-info/entry_points.txt
dasy_hy-0.24.2.dist-info/top_level.txt
dasy_hy-0.24.2.dist-info/RECORD
