Metadata-Version: 2.1
Name: dasy-hy
Version: 0.24.2
Summary: A Lisp dialect embedded in Python
Home-page: http://github.com/z80dev/hy
Author: Paul Tagliamonte
Author-email: tag@pault.ag
License: Expat
Project-URL: Source, https://github.com/z80dev/hy
Platform: any
Classifier: Development Status :: 4 - Beta
Classifier: Intended Audience :: Developers
Classifier: License :: DFSG approved
Classifier: License :: OSI Approved :: MIT License
Classifier: Operating System :: OS Independent
Classifier: Programming Language :: Lisp
Classifier: Programming Language :: Python
Classifier: Programming Language :: Python :: 3
Classifier: Programming Language :: Python :: 3.7
Classifier: Programming Language :: Python :: 3.8
Classifier: Programming Language :: Python :: 3.9
Classifier: Programming Language :: Python :: 3.10
Classifier: Topic :: Software Development :: Code Generators
Classifier: Topic :: Software Development :: Compilers
Classifier: Topic :: Software Development :: Libraries
Requires-Python: >= 3.7, < 3.12
License-File: LICENSE
License-File: AUTHORS
Requires-Dist: funcparserlib ~=1.0
Requires-Dist: colorama
Requires-Dist: astor >=0.8 ; python_version < "3.9"
